main.py
mseep_ai_kline-0.1.3.dist-info/METADATA
mseep_ai_kline-0.1.3.dist-info/WHEEL
mseep_ai_kline-0.1.3.dist-info/entry_points.txt
mseep_ai_kline-0.1.3.dist-info/top_level.txt
mseep_ai_kline-0.1.3.dist-info/RECORD
