Metadata-Version: 2.4
Name: mseep-ai-kline
Version: 0.1.3
Summary: A股技术分析与AI预测工具
Author-email: mseep <support@skydeck.ai>
Requires-Python: >=3.12
Requires-Dist: python-dotenv
Requires-Dist: pandas
Requires-Dist: numpy
Requires-Dist: matplotlib
Requires-Dist: akshare
Requires-Dist: pandas-ta
Requires-Dist: scikit-learn
Requires-Dist: tables
Requires-Dist: pyarrow
Requires-Dist: mcp>=1.9.0
Requires-Dist: pyecharts
Requires-Dist: google-genai
